enoceanmqtt/__init__.py
enoceanmqtt/communicator.py
enoceanmqtt/enoceanmqtt.py
enocean_mqtt-0.1.4.dist-info/LICENSE
enocean_mqtt-0.1.4.dist-info/METADATA
enocean_mqtt-0.1.4.dist-info/WHEEL
enocean_mqtt-0.1.4.dist-info/entry_points.txt
enocean_mqtt-0.1.4.dist-info/top_level.txt
enocean_mqtt-0.1.4.dist-info/RECORD
