Metadata-Version: 2.1
Name: enocean-mqtt
Version: 0.1.4
Summary: Receives messages from an enOcean serial interface (USB) and provides selected messages to an MQTT broker.
Home-page: https://github.com/embyt/enocean-mqtt
Author: Roman Morawek
Author-email: roman.morawek@embyt.com
License: GPLv3
Keywords: enOcean MQTT IoT
Classifier: Development Status :: 4 - Beta
Classifier: Intended Audience :: Developers
Classifier: License :: OSI Approved :: GNU General Public License v3 (GPLv3)
Classifier: Programming Language :: Python :: 3
License-File: LICENSE
Requires-Dist: enocean
Requires-Dist: paho-mqtt>=2
